biblearn/__init__.py
biblearn/sword.py
biblearn/util.py
biblearn/resources/sword/AKJV.zip
biblearn/resources/sword/ASV.zip
biblearn-0.0.2.dist-info/LICENSE
biblearn-0.0.2.dist-info/METADATA
biblearn-0.0.2.dist-info/WHEEL
biblearn-0.0.2.dist-info/top_level.txt
biblearn-0.0.2.dist-info/RECORD
