Metadata-Version: 2.1
Name: biblearn
Version: 0.0.2
Summary: Biblical Learning Toolkit (biblearn)
Home-page: https://github.com/hensh2ss/biblearn
Author: Seth S. Henshaw
Author-email: seth.henshaw@gmail.com
License: UNKNOWN
Project-URL: Bug Tracker, https://github.com/hensh2ss/biblearn/issues
Platform: UNKNOWN
Classifier: Programming Language :: Python :: 3
Classifier: License :: OSI Approved :: GNU General Public License v3 (GPLv3)
Classifier: Operating System :: OS Independent
Requires-Python: >=3.6
License-File: LICENSE
Requires-Dist: pysword
